cyberfusion/FoundryAgent/__init__.py
cyberfusion/FoundryAgent/api.py
cyberfusion/FoundryAgent/cli.py
cyberfusion/FoundryAgent/config.py
cyberfusion/FoundryAgent/modules/__init__.py
cyberfusion/FoundryAgent/modules/heartbeats.py
python3_cyberfusion_foundry_agent-1.0.1.dist-info/METADATA
python3_cyberfusion_foundry_agent-1.0.1.dist-info/WHEEL
python3_cyberfusion_foundry_agent-1.0.1.dist-info/entry_points.txt
python3_cyberfusion_foundry_agent-1.0.1.dist-info/top_level.txt
python3_cyberfusion_foundry_agent-1.0.1.dist-info/RECORD
