Metadata-Version: 2.4
Name: python3-cyberfusion-foundry-agent
Version: 1.0.1
Summary: VM/device agent for Foundry.
Author-email: Cyberfusion <support@cyberfusion.io>
Project-URL: Source, https://vcs.cyberfusion.nl/foundation/python3-cyberfusion-foundry-agent
Requires-Dist: requests==2.28.1
Requires-Dist: PyYAML==6.0
Requires-Dist: typer==0.7.0
